Metadata-Version: 2.1
Name: pyconquest
Version: 0.0.1
Summary: Python code which partly mimics the conquest pacs
Home-page: https://github.com/ReneMonshouwer/pyconquest
Author: René Monshouwer
Author-email: rene.monshouwer@radboudumc.nl
License: UNKNOWN
Platform: UNKNOWN
Classifier: Programming Language :: Python :: 3
Classifier: License :: OSI Approved :: MIT License
Classifier: Operating System :: OS Independent
Requires-Python: >=3.6
